autospider/__init__.py
autospider/auto_spider.py
autospider/utils.py
autospider-1.1.11.dist-info/LICENSE
autospider-1.1.11.dist-info/METADATA
autospider-1.1.11.dist-info/WHEEL
autospider-1.1.11.dist-info/top_level.txt
autospider-1.1.11.dist-info/RECORD
