Metadata-Version: 2.1
Name: autospider
Version: 1.1.11
Summary: A Smart, Automatic, Fast and Lightweight Web Scraper for Python
Home-page: https://github.com/khulnasoft-lab/autospider
Author: KhulnaSoft DevOps
Author-email: info@khulnasoft.com
License: MIT
Keywords: web scraping spider scraper
Classifier: Development Status :: 5 - Production/Stable
Classifier: License :: OSI Approved :: MIT License
Classifier: Programming Language :: Python :: 3
Classifier: Operating System :: OS Independent
Requires-Python: >=3.6
License-File: LICENSE
Requires-Dist: requests
Requires-Dist: beautifulsoup4
Requires-Dist: lxml
